browser_timeliner/__init__.py
browser_timeliner/analysis.py
browser_timeliner/anomaly_detector.py
browser_timeliner/categories.py
browser_timeliner/chromium_reader.py
browser_timeliner/cli.py
browser_timeliner/constants.py
browser_timeliner/domain_utils.py
browser_timeliner/exporter.py
browser_timeliner/firefox_reader.py
browser_timeliner/ingest.py
browser_timeliner/logging_config.py
browser_timeliner/models.py
browser_timeliner/preferences_parser.py
browser_timeliner/rule_engine.py
browser_timeliner/sessionizer.py
browser_timeliner/utils.py
browser_timeliner/rules/__init__.py
browser_timeliner/rules/default_rules.yaml
browser_timeliner-0.1.0.dist-info/METADATA
browser_timeliner-0.1.0.dist-info/WHEEL
browser_timeliner-0.1.0.dist-info/entry_points.txt
browser_timeliner-0.1.0.dist-info/RECORD
