Metadata-Version: 2.1
Name: browser-timeliner
Version: 0.1.0
Summary: Multi-browser artifact analysis toolkit
Author: Browser Timeliner Team
License: Proprietary
Requires-Python: ==3.11.*
Requires-Dist: pyyaml==6.0.1
Provides-Extra: test
Requires-Dist: pytest==8.2.2; extra == 'test'
